<?xml version='1.0' encoding='UTF-8'?>
<beans xmlns="http://www.springframework.org/schema/beans"
       xmlns:xsi="http://www.w3.org/2001/XMLSchema-instance"
       xsi:schemaLocation="http://www.springframework.org/schema/beans
          http://www.springframework.org/schema/beans/spring-beans-3.0.xsd">

    <!-- The bootstrap-context.xml file is used for patch definitions, importers, 
		 workflow, and loading custom content models.  -->

    <!-- Registration of new models-->
    <bean id="alfresco.dictionaryBootstrap" parent="dictionaryModelBootstrap" depends-on="dictionaryBootstrap">
        <property name="models">
            <list>
                <value>alfresco/module/${project.artifactId}/model/customModel.xml</value>
                <value>alfresco/module/${project.artifactId}/model/workflowModel.xml</value>
                <value>alfresco/module/${project.artifactId}/model/PSAL Form Model.xml</value>
            </list>
        </property>
        <property name="labels">
            <list>
                <value>alfresco/module/${project.artifactId}/messages/content-model</value>
                <value>alfresco/module/${project.artifactId}/messages/psgActions</value>
                <value>alfresco/module/${project.artifactId}/messages/psgWorkflow</value>
            </list>
        </property>
    </bean>


    <!-- Bootstrap folders -->

    <bean id="initialPSFoldersBootstrap" class="org.alfresco.repo.module.ImporterModuleComponent" parent="module.baseComponent">
        <property name="moduleId" value="${project.artifactId}" />
        <property name="name" value="initialPSFoldersBootstrap" />
        <property name="description" value="Bootstrap of initial folder in a new repository" />

        <property name="importer" ref="spacesBootstrap" />
        <property name="executeOnceOnly" value="true" />
        <property name="bootstrapViews">
            <list>
                <props>
                    <prop key="path">/app:company_home</prop>
                    <prop key="location">alfresco/module/${project.artifactId}/bootstrap/Filing Errors.acp</prop>
                </props>
                <props>
                    <prop key="path">/app:company_home</prop>
                    <prop key="location">alfresco/module/${project.artifactId}/bootstrap/Tasklists 19-6-2015.acp</prop>
                </props>
                <props>
                    <prop key="path">/app:company_home</prop>
                    <prop key="location">alfresco/module/${project.artifactId}/bootstrap/uploads.acp</prop>
                </props>
                <props>
                    <prop key="path">/app:company_home</prop>
                    <prop key="location">alfresco/module/${project.artifactId}/bootstrap/Workflow Errors.acp</prop>
                </props>
                <props>
                    <prop key="path">/app:company_home</prop>
                    <prop key="location">alfresco/module/${project.artifactId}/bootstrap/Services.acp</prop>
                </props>
            </list>
        </property>
    </bean>

</beans>
